sploitlib/__init__.py
sploitlib/config.py
sploitlib/http.py
sploitlib-0.1.2.dist-info/LICENSE
sploitlib-0.1.2.dist-info/METADATA
sploitlib-0.1.2.dist-info/WHEEL
sploitlib-0.1.2.dist-info/top_level.txt
sploitlib-0.1.2.dist-info/RECORD
