Metadata-Version: 2.1
Name: sploitlib
Version: 0.1.2
License-File: LICENSE
Requires-Dist: requests >=2.32.0
Requires-Dist: requests-toolbelt >=1.0.0
